abstractions/README.md
abstractions/__init__.py
abstractions/controller.py
abstractions/cqrs.py
abstractions/decorator.py
abstractions/dependency.py
abstractions/domain_events.py
abstractions/entity.py
abstractions/error.py
abstractions/factory.py
abstractions/mapper.py
abstractions/observer.py
abstractions/pipeline.py
abstractions/presenter.py
abstractions/repository.py
abstractions/result.py
abstractions/service.py
abstractions/specification.py
abstractions/strategy.py
abstractions/unit_of_work.py
abstractions/utility.py
abstractions/validator.py
abstractions/value_object.py
config/cache/config.json
config/db/config.json
config/security/config.json
configurations/README.md
configurations/cache.py
configurations/db.py
configurations/security.py
constants/README.md
constants/api_lk.py
constants/api_status.py
constants/default.py
constants/filter_operator.py
constants/payload_type.py
constants/regular_expression.py
constants/db/table.py
controllers/README.md
controllers/apis/__init__.py
controllers/apis/abstraction.py
controllers/apis/v1/__init__.py
controllers/apis/v1/abstraction.py
controllers/product/__init__.py
controllers/user/__init__.py
controllers/user/abstraction.py
controllers/user/login.py
controllers/user/logout.py
controllers/user/register.py
core/README.md
core/__init__.py
core/features/__init__.py
core/features/flags.py
core/health/__init__.py
core/health/checks.py
core/health/router.py
core/observability/__init__.py
core/observability/audit.py
core/observability/logging.py
core/observability/metrics.py
core/observability/tracing.py
core/resilience/__init__.py
core/resilience/circuit_breaker.py
core/resilience/retry.py
core/security/__init__.py
core/security/api_keys.py
core/security/encryption.py
core/security/webhooks.py
core/tasks/__init__.py
core/tasks/queue.py
core/tenancy/__init__.py
core/tenancy/context.py
core/tenancy/middleware.py
core/testing/__init__.py
core/testing/factories.py
core/testing/fixtures.py
core/testing/mocks.py
pyfastmvc-1.4.0.dist-info/licenses/LICENSE
pyfastmvc-1.4.0.dist-info/METADATA
pyfastmvc-1.4.0.dist-info/WHEEL
pyfastmvc-1.4.0.dist-info/entry_points.txt
pyfastmvc-1.4.0.dist-info/top_level.txt
pyfastmvc-1.4.0.dist-info/RECORD
