Metadata-Version: 2.4
Name: pyfastmvc
Version: 1.4.0
Summary: Production-grade MVC Framework for FastAPI - Generate projects, entities, and migrations with a single command
Author-email: Shivansh Sengar <sengarsinghshivansh@gmail.com>, Shreyansh Sengar <sengarsinghshreyansh@gmail.com>
Maintainer-email: Shivansh Sengar <sengarsinghshivansh@gmail.com>, Shreyansh Sengar <sengarsinghshreyansh@gmail.com>
License: MIT
Project-URL: Homepage, https://github.com/shregar1/fastMVC
Project-URL: Documentation, https://fastapi-mvc.dev/docs
Project-URL: Repository, https://github.com/shregar1/fastMVC
Project-URL: Issues, https://github.com/shregar1/fastMVC/issues
Project-URL: Changelog, https://github.com/shregar1/fastMVC/blob/main/CHANGELOG.md
Keywords: fastapi,mvc,framework,api,rest,web,backend,python,scaffold,generator,crud,authentication,jwt,sqlalchemy,pydantic,alembic,migrations,redis,caching
Classifier: Development Status :: 4 - Beta
Classifier: Environment :: Console
Classifier: Environment :: Web Environment
Classifier: Framework :: FastAPI
Classifier: Intended Audience :: Developers
Classifier: Intended Audience :: Information Technology
Classifier: License :: OSI Approved :: MIT License
Classifier: Natural Language :: English
Classifier: Operating System :: OS Independent
Classifier: Programming Language :: Python
Classifier: Programming Language :: Python :: 3
Classifier: Programming Language :: Python :: 3 :: Only
Classifier: Programming Language :: Python :: 3.10
Classifier: Programming Language :: Python :: 3.11
Classifier: Programming Language :: Python :: 3.12
Classifier: Programming Language :: Python :: 3.13
Classifier: Topic :: Internet
Classifier: Topic :: Internet :: WWW/HTTP
Classifier: Topic :: Internet :: WWW/HTTP :: HTTP Servers
Classifier: Topic :: Software Development
Classifier: Topic :: Software Development :: Code Generators
Classifier: Topic :: Software Development :: Libraries
Classifier: Topic :: Software Development :: Libraries :: Application Frameworks
Classifier: Topic :: Software Development :: Libraries :: Python Modules
Classifier: Typing :: Typed
Requires-Python: >=3.10
License-File: LICENSE
Requires-Dist: click<9.0.0,>=8.0.0
Requires-Dist: fastapi<1.0.0,>=0.100.0
Requires-Dist: uvicorn<1.0.0,>=0.20.0
Requires-Dist: starlette<1.0.0,>=0.27.0
Requires-Dist: pydantic<3.0.0,>=2.0.0
Requires-Dist: sqlalchemy<3.0.0,>=2.0.0
Requires-Dist: alembic<2.0.0,>=1.10.0
Requires-Dist: python-dotenv<2.0.0,>=1.0.0
Requires-Dist: loguru<1.0.0,>=0.7.0
Requires-Dist: pyjwt<3.0.0,>=2.8.0
Requires-Dist: bcrypt<5.0.0,>=4.0.0
Requires-Dist: redis<7.0.0,>=4.0.0
Requires-Dist: psycopg2-binary<3.0.0,>=2.9.0
Requires-Dist: email-validator<3.0.0,>=2.0.0
Requires-Dist: python-ulid<3.0.0,>=1.0.0
Requires-Dist: httpx<1.0.0,>=0.24.0
Requires-Dist: cachetools<6.0.0,>=5.0.0
Requires-Dist: mako<2.0.0,>=1.2.0
Requires-Dist: fastmvc-middleware>=0.6.2
Requires-Dist: cryptography<44.0.0,>=41.0.0
Provides-Extra: dev
Requires-Dist: pytest<9.0.0,>=7.0.0; extra == "dev"
Requires-Dist: pytest-asyncio<1.0.0,>=0.21.0; extra == "dev"
Requires-Dist: pytest-cov<6.0.0,>=4.0.0; extra == "dev"
Requires-Dist: pytest-mock<4.0.0,>=3.10.0; extra == "dev"
Requires-Dist: coverage<8.0.0,>=7.0.0; extra == "dev"
Requires-Dist: time-machine<3.0.0,>=2.10.0; extra == "dev"
Requires-Dist: ruff<1.0.0,>=0.1.0; extra == "dev"
Requires-Dist: twine<6.0.0,>=4.0.0; extra == "dev"
Requires-Dist: build<2.0.0,>=1.0.0; extra == "dev"
Provides-Extra: docs
Requires-Dist: mkdocs>=1.5.0; extra == "docs"
Requires-Dist: mkdocs-material>=9.0.0; extra == "docs"
Requires-Dist: mkdocstrings[python]>=0.24.0; extra == "docs"
Provides-Extra: all
Requires-Dist: pyfastmvc[dev,docs]; extra == "all"
Dynamic: license-file
